{
  "book-room": [
    {
      "id": "324e",
      "time": "14h ",
      "Fullname": "Bùi Minh Diện",
      "phone": "dsa",
      "email": "sad",
      "services": [
        "thuê xe máy"
      ],
      "gift": "mũ",
      "date": [
        "15/10/2024",
        "13/11/2024"
      ]
    },
    {
      "id": "aefb",
      "time": "14h ",
      "Fullname": "Bùi Minh Diện",
      "phone": "dsa",
      "email": "sad",
      "services": [
        "thuê xe máy"
      ],
      "gift": "mũ",
      "date": [
        "15/10/2024",
        "13/11/2024"
      ]
    },
    {
      "id": "7dfb",
      "time": "14h "
    },
    {
      "id": "97cd",
      "time": "14h ",
      "Fullname": "Bùi Minh Diện",
      "phone": "dsa",
      "email": "sad",
      "services": [
        "thuê xe máy",
        "thuê oto 4 chỗ",
        "thuê oto 7 chỗ",
        "thuê oto 14 chỗ"
      ],
      "date": [
        "08/11/2024",
        "28/11/2024"
      ],
      "gift": "mũ"
    },
    {
      "id": "ad8f",
      "time": "14h ",
      "Fullname": "Bùi Minh Diện",
      "phone": "dsa",
      "email": "sad",
      "services": [
        "thuê xe máy"
      ],
      "gift": "mũ",
      "date": [
        "16/10/2024",
        "19/11/2024"
      ]
    },
    {
      "id": "5082",
      "time": "14h ",
      "Fullname": "Bùi Minh Diện",
      "phone": "dsa",
      "email": "aádad",
      "services": [
        "thuê xe máy"
      ],
      "gift": "mũ",
      "date": [
        "16/10/2024",
        "19/11/2024"
      ]
    },
    {
      "id": "1169",
      "time": "14h ",
      "Fullname": "Bùi Minh Diện",
      "phone": "dsa",
      "email": "aádad",
      "date": [
        "19/10/2024",
        "20/11/2024"
      ]
    },
    {
      "id": "7502",
      "time": "10 giờ",
      "Fullname": "Bùi Minh Diện",
      "phone": "dsa",
      "email": "aádad",
      "date": [
        "17/10/2024",
        "20/11/2024"
      ],
      "gift": "mũ",
      "services": [
        "thuê oto 4 chỗ"
      ]
    },
    {
      "id": "4e90",
      "time": "14h ",
      "Fullname": "Bùi Minh Diện",
      "phone": "dsa",
      "email": "aádad",
      "date": [
        "08/10/2024",
        "26/11/2024"
      ],
      "services": [
        "thuê xe máy",
        "thuê oto 14 chỗ"
      ],
      "gift": "áo cộc"
    },
    {
      "id": "6e08",
      "time": "14h ",
      "Fullname": "Bùi Minh Diện",
      "phone": "dsa",
      "email": "sad"
    }
  ],
  "Rooms": [
    {
      "id": "9c09",
      "name": "Nam Định122",
      "quatitybed": 12,
      "quatitypeople": 1,
      "yeu cầu": [
        "wifi",
        "nóng lạnh",
        "điều hòa"
      ],
      "decription": "ngon",
      "status": false,
      "typeroom": true
    },
    {
      "id": "8737",
      "name": "Nam Định",
      "quatitybed": 12,
      "quatitypeople": 1,
      "yeu cầu": [
        "wifi",
        "nóng lạnh",
        "điều hòa"
      ],
      "decription": "dsa",
      "status": true
    },
    {
      "id": "1144",
      "name": "Khánh Hòa",
      "quatitybed": 12,
      "quatitypeople": 12,
      "yeu cầu": [
        "wifi",
        "nóng lạnh"
      ],
      "decription": "ngon",
      "status": false,
      "typeroom": true
    },
    {
      "id": "49d9",
      "name": "Khánh Hòa 1",
      "quatitybed": 12,
      "quatitypeople": 3,
      "yeu cầu": [
        "nóng lạnh",
        "wifi",
        "điều hòa"
      ],
      "decription": "ngon",
      "status": true,
      "typeroom": true
    },
    {
      "id": "2164",
      "name": "dsad",
      "quatitybed": 12,
      "quatitypeople": 12,
      "yeu cầu": [
        "điều hòa",
        "wifi",
        "nóng lạnh"
      ],
      "decription": "qưe",
      "status": true
    },
    {
      "id": "b69a",
      "name": "Lào Cai",
      "quatitybed": 2,
      "quatitypeople": 12,
      "yeu cầu": [
        "điều hòa",
        "nóng lạnh",
        "wifi"
      ],
      "decription": "sạch đẹp",
      "status": true,
      "typeroom": true
    },
    {
      "id": "4434",
      "name": "dsad",
      "quatitybed": 12,
      "quatitypeople": 123,
      "yeu cầu": [
        "wifi",
        "nóng lạnh",
        "điều hòa"
      ],
      "decription": "31",
      "status": true,
      "typeroom": true
    }
  ]
}